{
  "type": "minecraft:crafting_shaped",
  "pattern": [
    "S S",
    "E E"
  ],
  "key": {
    "S": [
      "minecraft:nether_star"
    ],
    "E": [
      "minecraft:dragon_egg"
    ]
  },
  "result": {
    "id": "minecraft:netherite_boots",
    "components": {
      "minecraft:attribute_modifiers": [
        {
          "type": "minecraft:max_health",
          "id": "1",
          "amount": 4,
          "operation": "add_value",
          "slot": "feet"
        },
        {
          "type": "minecraft:armor",
          "id": "2",
          "amount": 4,
          "operation": "add_value",
          "slot": "feet"
        },
        {
          "type": "minecraft:armor_toughness",
          "id": "3",
          "amount": 4,
          "operation": "add_value",
          "slot": "feet"
        },
        {
          "type": "minecraft:knockback_resistance",
          "id": "4",
          "amount": 0.1,
          "operation": "add_value",
          "slot": "feet"
        },
        {
          "type": "minecraft:step_height",
          "id": "5",
          "amount": 0.5,
          "operation": "add_value",
          "slot": "feet"
        }
      ],
      "minecraft:custom_name": {
        "text": "Dragon Boots",
        "type": "text",
        "color": "dark_purple"
      },
      "minecraft:max_damage": 1000
    },
    "count": 1
  }
}